AUTHORS
CONTRIBUTING.md
LICENSE
MANIFEST.in
README.md
setup.cfg
setup.py
bpptkg_richter.egg-info/PKG-INFO
bpptkg_richter.egg-info/SOURCES.txt
bpptkg_richter.egg-info/dependency_links.txt
bpptkg_richter.egg-info/not-zip-safe
bpptkg_richter.egg-info/requires.txt
bpptkg_richter.egg-info/top_level.txt
richter/__init__.py
richter/link.py
richter/ml.py
richter/paz.py
richter/utils.py
richter/version.py