Metadata-Version: 2.1
Name: bpptkg-richter
Version: 1.0.0
Summary: Python library for computing Richter local magnitude scales on BPPTKG seismic network
Home-page: https://github.com/bpptkg/bpptkg-richter
Author: BPPTKG
Author-email: bpptkg@esdm.go.id
License: MIT
Platform: UNKNOWN
Classifier: Development Status :: 5 - Production/Stable
Classifier: Environment :: Console
Classifier: Operating System :: POSIX :: Linux
Classifier: Intended Audience :: Science/Research
Classifier: Natural Language :: English
Classifier: Programming Language :: Python :: 3.6
Classifier: Programming Language :: Python :: 3.7
Classifier: Programming Language :: Python :: 3.8
Classifier: Programming Language :: Python :: 3.9
